{
  "attributes": {
    "sys_dns_public/tags": {
      "choice": [

      ],
      "description": "DNS Tag space to query for public ips to set on multiple records",
      "calculated": false,
      "type": "string",
      "display_name": "DNS Tag Space",
      "required": "required",
      "recipes": [

      ]
    },
    "sys_dns/id": {
      "choice": [

      ],
      "description": "The unique identifier that is associated with the DNS A record of the server. The unique identifier is assigned by the DNS provider when you create a dynamic DNS A record. This ID is used to update the associated A record with the private IP address of the server when this recipe is run. If you are using DNS Made Easy as your DNS provider, a 7-digit number is used (e.g., 4403234). If you are using Cloud DNS, provide both Domain ID and Record ID (e.g., DomainID:A-RecordID)",
      "calculated": false,
      "type": "string",
      "display_name": "DNS Record ID",
      "required": "required",
      "recipes": [

      ]
    }
  },
  "conflicting": {
  },
  "name": "sys_dns_public",
  "providing": {
  },
  "dependencies": {
    "sys_dns": ">= 0.0.0",
    "rightscale": ">= 0.0.0"
  },
  "long_description": "Description\n===========\n\nRequirements\n============\n\nAttributes\n==========\n\nUsage\n=====\n\n",
  "groupings": {
  },
  "maintainer_email": "premium@rightscale.com",
  "maintainer": "RightScale Inc",
  "description": "Installs/Configures sys_dns_public",
  "version": "0.1.0",
  "replacing": {
  },
  "suggestions": {
  },
  "license": "Apache 2.0",
  "recipes": {
    "sys_dns_public::do_aws_create_health_check": "creates aws health_check",
    "sys_dns_public::set_public_ip_by_tag": "Sets IP Records by tag",
    "sys_dns_public::do_set_public": "Sets the DNS Record to the Public IP"
  },
  "recommendations": {
  },
  "platforms": {
  }
}